opticsyCUDA/FDTD.cp312-win_amd64.pyd
opticsyCUDA/FDTD4.cp312-win_amd64.pyd
opticsyCUDA/Utils.cp312-win_amd64.pyd
torchopticsy/Diffraction.py
torchopticsy/ETM.py
torchopticsy/Interference.py
torchopticsy/Optimization.py
torchopticsy/Properties.py
torchopticsy/Utils.py
torchopticsy/__init__.py
torchopticsy/mma.py
torchopticsy/FDTD/Recorder.py
torchopticsy/FDTD/Solver.py
torchopticsy/FDTD/Source.py
torchopticsy/FDTD/Structure.py
torchopticsy/FDTD/__init__.py
torchopticsy-1.1.4.dist-info/METADATA
torchopticsy-1.1.4.dist-info/WHEEL
torchopticsy-1.1.4.dist-info/top_level.txt
torchopticsy-1.1.4.dist-info/RECORD
