Metadata-Version: 2.1
Name: torchopticsy
Version: 1.1.4
Summary: PyTorch-based optics calculations with CUDA acceleration
Author: YuningYe
Author-email: 1956860113@qq.com
Requires-Dist: torch >=1.10
Requires-Dist: opencv-python >=4.5
Requires-Dist: matplotlib >=3.3
Requires-Dist: tqdm >=4.60
Requires-Dist: scipy >=1.5
Requires-Dist: ipywidgets >=7.0
Requires-Dist: IPython >=7.0
